su2fmt/__init__.py
su2fmt/exporter.py
su2fmt/mesh.py
su2fmt/parser.py
su2fmt-2.0.0.dist-info/LICENSE
su2fmt-2.0.0.dist-info/METADATA
su2fmt-2.0.0.dist-info/WHEEL
su2fmt-2.0.0.dist-info/top_level.txt
su2fmt-2.0.0.dist-info/RECORD
