Metadata-Version: 2.1
Name: su2fmt
Version: 2.0.0
Summary: the open source SU2 mesh format parser and exporter
Author: Afshawn Lotfi
Author-email: 
License-File: LICENSE
Requires-Dist: numpy
